sweetautocomplete/__init__.py
sweetautocomplete/apps.py
sweetautocomplete/autocomplete.py
sweetautocomplete/settings.py
sweetautocomplete/urls.py
sweetautocomplete/views.py
django_sweet_autocomplete-1.2.0.dist-info/METADATA
django_sweet_autocomplete-1.2.0.dist-info/WHEEL
django_sweet_autocomplete-1.2.0.dist-info/top_level.txt
django_sweet_autocomplete-1.2.0.dist-info/RECORD
