Metadata-Version: 2.1
Name: django-sweet-autocomplete
Version: 1.2.0
Summary: Simplify autocomplete functionalities implementation in your Django project.
Home-page: https://github.com/kubeljk/django-sweet-autocomplete
Author: Klemen Kubelj
Author-email: klemen.kubelj@gmail.com
License: MIT
Keywords: django autocomplete
Classifier: Environment :: Web Environment
Classifier: Framework :: Django
Classifier: Framework :: Django :: 4.2
Classifier: Programming Language :: Python
Classifier: Programming Language :: Python :: 3.12
Classifier: Topic :: Internet :: WWW/HTTP
Classifier: Topic :: Internet :: WWW/HTTP :: Dynamic Content
Classifier: License :: OSI Approved :: MIT License
Requires-Dist: Django>=3.2
Requires-Dist: djangorestframework>=3
Requires-Dist: psycopg2-binary>=2.8
